forcolate/__init__.py
forcolate/bullet_point_workflow.py
forcolate/common.py
forcolate/document_to_text.py
forcolate/folder_search.py
forcolate/outlook_search.py
forcolate/query_url_extractor.py
forcolate/remote_LLM.py
forcolate/summary_extractor.py
forcolate/tool_selector.py
forcolate/url_to_text.py
forcolate/vendors/ms-marco-MiniLM-L6-v2/config.json
forcolate/vendors/ms-marco-MiniLM-L6-v2/model.safetensors
forcolate/vendors/ms-marco-MiniLM-L6-v2/tokenizer_config.json
forcolate/vendors/ms-marco-MiniLM-L6-v2/vocab.txt
forcolate-0.1.18.dist-info/licenses/LICENSE
forcolate-0.1.18.dist-info/METADATA
forcolate-0.1.18.dist-info/WHEEL
forcolate-0.1.18.dist-info/top_level.txt
forcolate-0.1.18.dist-info/RECORD
