Metadata-Version: 2.4
Name: forcolate
Version: 0.1.18
Summary: A library for semantic search in local environment
Author-email: FOR Team <jonathan.sprauel@irt-saintexupery.com>
Project-URL: Homepage, https://github.com/FOR-sight-ai/FORcolate
Project-URL: Bug Tracker, https://github.com/FOR-sight-ai/FORcolate/issues
Classifier: Programming Language :: Python :: 3
Classifier: License :: OSI Approved :: MIT License
Classifier: Operating System :: OS Independent
Requires-Python: >=3.6
License-File: LICENSE
Requires-Dist: pywin32; platform_system == "Windows"
Requires-Dist: fastembed
Requires-Dist: docling
Requires-Dist: py7zr
Dynamic: license-file
